AI2GIS/__init__.py
AI2GIS/_utils.py
AI2GIS/converter.py
AI2GIS/io.py
AI2GIS/process_src.py
AI2GIS/types.py
ai2gis-0.1.1.dist-info/METADATA
ai2gis-0.1.1.dist-info/WHEEL
ai2gis-0.1.1.dist-info/top_level.txt
ai2gis-0.1.1.dist-info/RECORD
