Metadata-Version: 2.4
Name: AI2GIS
Version: 0.1.1
Summary: Thư viện Python để chuyển đổi kết quả AI sang định dạng GIS
Author-email: TheToanDiep <toand.diep.e@ctuav.vn>
License: MIT
Project-URL: Homepage, https://gitlab.ctgroupvietnam.com/ctuav-data-ai/gis-conversion
Classifier: Programming Language :: Python :: 3
Classifier: License :: OSI Approved :: MIT License
Classifier: Operating System :: OS Independent
Classifier: Topic :: Scientific/Engineering :: GIS
Requires-Python: >=3.8
Requires-Dist: rasterio
Requires-Dist: geopandas
Requires-Dist: shapely
Requires-Dist: numpy
Requires-Dist: scipy
Requires-Dist: opencv-python
Requires-Dist: numba
Requires-Dist: scikit-image
Requires-Dist: topojson
Requires-Dist: fiona
